CHANGES.txt
LICENSE.txt
MANIFEST.in
README.txt
ez_setup.py
protlib.py
setup.py
unit_tests.py
examples/ctype_subclassing/testing.py
examples/custom_logging/testing.py
examples/geocalc/client.py
examples/geocalc/common.py
examples/geocalc/server.py
examples/struct_inheritance/client.py
examples/struct_inheritance/common.py
examples/struct_inheritance/server.py
protlib.egg-info/PKG-INFO
protlib.egg-info/SOURCES.txt
protlib.egg-info/dependency_links.txt
protlib.egg-info/top_level.txt